floxcore/__init__.py
floxcore/command.py
floxcore/config.py
floxcore/console.py
floxcore/context.py
floxcore/exceptions.py
floxcore/plugin.py
floxcore/remotes.py
floxcore/secrets.py
floxcore/settings.py
floxcore/shell.py
floxcore/state.py
floxcore/utils/__init__.py
floxcore/utils/dir.py
floxcore/utils/functions.py
floxcore/utils/string.py
floxcore/utils/table.py
flox_core-0.2.0.dist-info/LICENSE
flox_core-0.2.0.dist-info/WHEEL
flox_core-0.2.0.dist-info/METADATA
flox_core-0.2.0.dist-info/RECORD
