Metadata-Version: 2.1
Name: flox-core
Version: 0.2.0
Summary: Core library for flox
License: MIT
Author: Michal Przytulski
Author-email: michal@przytulski.pl
Requires-Python: >=3.6.2,<4.0.0
Classifier: License :: OSI Approved :: MIT License
Classifier: Programming Language :: Python :: 3
Classifier: Programming Language :: Python :: 3.7
Classifier: Programming Language :: Python :: 3.8
Requires-Dist: anyconfig (>=0.10,<0.11)
Requires-Dist: click (>=7.1,<8.0)
Requires-Dist: lazy-load (>=0.8.2,<0.9.0)
Requires-Dist: loguru (>=0.5,<0.6)
Requires-Dist: plumbum (>=1.7,<2.0)
Requires-Dist: python-box (>=5.3,<6.0)
Requires-Dist: toml (>=0.10.2,<0.11.0)
Requires-Dist: tqdm (>=4.58,<5.0)
Requires-Dist: wasabi (>=0.9,<0.10)
